MANIFEST.in
README.rst
Version
requirements.txt
setup.py
Flask_Cache_Redis_Cluster.egg-info/PKG-INFO
Flask_Cache_Redis_Cluster.egg-info/SOURCES.txt
Flask_Cache_Redis_Cluster.egg-info/dependency_links.txt
Flask_Cache_Redis_Cluster.egg-info/requires.txt
Flask_Cache_Redis_Cluster.egg-info/top_level.txt
flask_cache_redis_cluster/__init__.py