Metadata-Version: 1.1
Name: Flask-Cache-Redis-Cluster
Version: 0.0.5
Summary: Adds redis cluster caching support to the Flask Cache(ing) extension
Home-page: https://github.com/Richard-Mathie/Flask-Cache-Redis-Cluster
Author: Richard Mathie
Author-email: richard.mathie@cantab.net
License: BSD
Platform: any
Classifier: Environment :: Web Environment
Classifier: Intended Audience :: Developers
Classifier: License :: OSI Approved :: BSD License
Classifier: Operating System :: OS Independent
Classifier: Programming Language :: Python
Classifier: Programming Language :: Python :: 2
Classifier: Programming Language :: Python :: 2.6
Classifier: Programming Language :: Python :: 2.7
